INWX/Domrobot.py
INWX/__init__.py
inwx_domrobot-3.2.0.dist-info/LICENSE
inwx_domrobot-3.2.0.dist-info/METADATA
inwx_domrobot-3.2.0.dist-info/WHEEL
inwx_domrobot-3.2.0.dist-info/top_level.txt
inwx_domrobot-3.2.0.dist-info/RECORD
