Metadata-Version: 2.1
Name: inwx-domrobot
Version: 3.2.0
Summary: INWX API Python Client
Home-page: https://github.com/inwx/python-client
Download-URL: https://github.com/inwx/python-client/archive/v3.2.0.tar.gz
Author: INWX Developer
Author-email: developer@inwx.de
Keywords: INWX,API,PYTHON,CLIENT,DOMROBOT
Classifier: Development Status :: 5 - Production/Stable
Classifier: Intended Audience :: Developers
Classifier: Topic :: Software Development
Classifier: License :: OSI Approved :: MIT License
Classifier: Programming Language :: Python :: 3.5
Classifier: Programming Language :: Python :: 3.6
Classifier: Programming Language :: Python :: 3.7
Classifier: Programming Language :: Python :: 3.8
Classifier: Programming Language :: Python :: 3.9
Classifier: Programming Language :: Python :: 3.10
License-File: LICENSE
Requires-Dist: requests
